<?xml version="1.0" encoding="UTF-8"?>
<testcase>
    <brief>Forwarding and Routing traffic based on policy, oif is tunnel on wifi0 interface Platform  Dependence BR100,BR200,BR200-WP,BRAP330,BRAP350,BRAP121,BRAP141</brief>
    <priority>Middle</priority>
    <automated>no</automated>
    <description>
        
		Pre-Condition:

			1.	Set interface wifi0 mode wan
			2.	Create one l3 tunnel between BR wifi0 and CVG eth0

		Test Procedure:

			1.	Create a routing policy
			2.	Set a match-map 
			3.	Set a route-map, the oif for all traffic is tunnel on wifi0 interface, and 
			bind the route-map to a match-map
			4.	Bind one match-map to routing policy
			5.	Laptop connect to the match-map
			6.	Laptop send traffic to vpn network, check result1
			7.	Laptop send traffic to internet, check result2
			8.	tunnel down
			9.	Laptop send traffic to vpn network, check result3
			10.	Laptop send traffic to internet, check result3
			11.	tunnel up
			12.	Laptop send traffic to vpn network, check result1
			13.	Laptop send traffic to internet, check result2
			14.	wifi0 down(and the tunnel down)
			15.	Laptop send traffic to vpn network, check result3
			16.	Laptop send traffic to internet, check result3
			17.	wifi0 up and tunnel up on wifi0
			18.	Laptop send traffic to vpn network, check result1
			19.	Laptop send traffic to internet, check result2
    </description>
    <numofap>1</numofap>
    <numofsta>1</numofsta>
    <tbtype>winlin</tbtype>
    <property name="" value=""/>
    <stage>
                <step no="1">
            <desc>
            1.	Set interface wifi0 mode wan
            </desc>
            <log-file></log-file>
            <telnet target="ap1"></telnet>
            <ssh target="sta1"></ssh>
            <setvar name=""></setvar>
            <script></script>
            <log-match></log-match>
        </step>
        <step no="2">
            <desc>
            2.	Create one l3 tunnel between BR wifi0 and CVG eth0
            </desc>
            <log-file></log-file>
            <telnet target="ap1"></telnet>
            <ssh target="sta1"></ssh>
            <setvar name=""></setvar>
            <script></script>
            <log-match></log-match>
        </step>
        <step no="3">
            <desc>
            1.	Create a routing policy
            </desc>
            <log-file></log-file>
            <telnet target="ap1"></telnet>
            <ssh target="sta1"></ssh>
            <setvar name=""></setvar>
            <script></script>
            <log-match></log-match>
        </step>
        <step no="4">
            <desc>
            2.	Set a match-map 
            </desc>
            <log-file></log-file>
            <telnet target="ap1"></telnet>
            <ssh target="sta1"></ssh>
            <setvar name=""></setvar>
            <script></script>
            <log-match></log-match>
        </step>
        <step no="5">
            <desc>
            3.	Set a route-map, the oif for all traffic is tunnel on wifi0 interface, and 
				bind the route-map to a match-map
            </desc>
            <log-file></log-file>
            <telnet target="ap1"></telnet>
            <ssh target="sta1"></ssh>
            <setvar name=""></setvar>
            <script></script>
            <log-match></log-match>
        </step>
        <step no="6">
            <desc>
            4.	Bind one match-map to routing policy
            </desc>
            <log-file></log-file>
            <telnet target="ap1"></telnet>
            <ssh target="sta1"></ssh>
            <setvar name=""></setvar>
            <script></script>
            <log-match></log-match>
        </step>
        <step no="7">
            <desc>
            5.	Laptop connect to the match-map
            </desc>
            <log-file></log-file>
            <telnet target="ap1"></telnet>
            <ssh target="sta1"></ssh>
            <setvar name=""></setvar>
            <script></script>
            <log-match></log-match>
        </step>
        <step no="8">
            <desc>
            6.	Laptop send traffic to vpn network, check result1
            </desc>
            <log-file></log-file>
            <telnet target="ap1"></telnet>
            <ssh target="sta1"></ssh>
            <setvar name=""></setvar>
            <script></script>
            <log-match></log-match>
        </step>
        <step no="9">
            <desc>
            7.	Laptop send traffic to internet, check result2
            </desc>
            <log-file></log-file>
            <telnet target="ap1"></telnet>
            <ssh target="sta1"></ssh>
            <setvar name=""></setvar>
            <script></script>
            <log-match></log-match>
        </step>
        <step no="10">
            <desc>
            8.	tunnel down
            </desc>
            <log-file></log-file>
            <telnet target="ap1"></telnet>
            <ssh target="sta1"></ssh>
            <setvar name=""></setvar>
            <script></script>
            <log-match></log-match>
        </step>
        <step no="11">
            <desc>
            9.	Laptop send traffic to vpn network, check result3
            </desc>
            <log-file></log-file>
            <telnet target="ap1"></telnet>
            <ssh target="sta1"></ssh>
            <setvar name=""></setvar>
            <script></script>
            <log-match></log-match>
        </step>
        <step no="12">
            <desc>
            10.	Laptop send traffic to internet, check result3
            </desc>
            <log-file></log-file>
            <telnet target="ap1"></telnet>
            <ssh target="sta1"></ssh>
            <setvar name=""></setvar>
            <script></script>
            <log-match></log-match>
        </step>
        <step no="13">
            <desc>
            11.	tunnel up
            </desc>
            <log-file></log-file>
            <telnet target="ap1"></telnet>
            <ssh target="sta1"></ssh>
            <setvar name=""></setvar>
            <script></script>
            <log-match></log-match>
        </step>
        <step no="14">
            <desc>
            12.	Laptop send traffic to vpn network, check result1
            </desc>
            <log-file></log-file>
            <telnet target="ap1"></telnet>
            <ssh target="sta1"></ssh>
            <setvar name=""></setvar>
            <script></script>
            <log-match></log-match>
        </step>
        <step no="15">
            <desc>
            13.	Laptop send traffic to internet, check result2
            </desc>
            <log-file></log-file>
            <telnet target="ap1"></telnet>
            <ssh target="sta1"></ssh>
            <setvar name=""></setvar>
            <script></script>
            <log-match></log-match>
        </step>
        <step no="16">
            <desc>
            14.	wifi0 down(and the tunnel down)
            </desc>
            <log-file></log-file>
            <telnet target="ap1"></telnet>
            <ssh target="sta1"></ssh>
            <setvar name=""></setvar>
            <script></script>
            <log-match></log-match>
        </step>
        <step no="17">
            <desc>
            15.	Laptop send traffic to vpn network, check result3
            </desc>
            <log-file></log-file>
            <telnet target="ap1"></telnet>
            <ssh target="sta1"></ssh>
            <setvar name=""></setvar>
            <script></script>
            <log-match></log-match>
        </step>
        <step no="18">
            <desc>
            16.	Laptop send traffic to internet, check result3
            </desc>
            <log-file></log-file>
            <telnet target="ap1"></telnet>
            <ssh target="sta1"></ssh>
            <setvar name=""></setvar>
            <script></script>
            <log-match></log-match>
        </step>
        <step no="19">
            <desc>
            17.	wifi0 up and tunnel up on wifi0
            </desc>
            <log-file></log-file>
            <telnet target="ap1"></telnet>
            <ssh target="sta1"></ssh>
            <setvar name=""></setvar>
            <script></script>
            <log-match></log-match>
        </step>
        <step no="20">
            <desc>
            18.	Laptop send traffic to vpn network, check result1
            </desc>
            <log-file></log-file>
            <telnet target="ap1"></telnet>
            <ssh target="sta1"></ssh>
            <setvar name=""></setvar>
            <script></script>
            <log-match></log-match>
        </step>
        <step no="21">
            <desc>
            19.	Laptop send traffic to internet, check result2
            </desc>
            <log-file></log-file>
            <telnet target="ap1"></telnet>
            <ssh target="sta1"></ssh>
            <setvar name=""></setvar>
            <script></script>
            <log-match></log-match>
        </step>

    </stage>
    <failed-process>
        <step no="1..n">
            .. process
	</step>
    </failed-process>
</testcase>
