<?xml version="1.0" encoding="UTF-8"?>
<testcase>
    <brief>create and delete user-group continually</brief>
    <priority>High</priority>
    <automated>no</automated>
    <description>
        
		Pre-Condition:

			One client connect to AP, back traffic is running

		Test Procedure:

			-create 512 user-group
			-save result
			-delete the user-group
			-save result
			-redo the previous process
    </description>
    <numofap>1</numofap>
    <numofsta>1</numofsta>
    <tbtype>winlin</tbtype>
    <property name="" value=""/>
    <stage>
                <step no="1">
            <desc>
            
				One client connect to AP, back traffic is running
            </desc>
            <log-file></log-file>
            <telnet target="ap1"></telnet>
            <ssh target="sta1"></ssh>
            <setvar name=""></setvar>
            <script></script>
            <log-match></log-match>
        </step>
        <step no="2">
            <desc>
            -create 512 user-group
            </desc>
            <log-file></log-file>
            <telnet target="ap1"></telnet>
            <ssh target="sta1"></ssh>
            <setvar name=""></setvar>
            <script></script>
            <log-match></log-match>
        </step>
        <step no="3">
            <desc>
            -save result
            </desc>
            <log-file></log-file>
            <telnet target="ap1"></telnet>
            <ssh target="sta1"></ssh>
            <setvar name=""></setvar>
            <script></script>
            <log-match></log-match>
        </step>
        <step no="4">
            <desc>
            -delete the user-group
            </desc>
            <log-file></log-file>
            <telnet target="ap1"></telnet>
            <ssh target="sta1"></ssh>
            <setvar name=""></setvar>
            <script></script>
            <log-match></log-match>
        </step>
        <step no="5">
            <desc>
            -save result
            </desc>
            <log-file></log-file>
            <telnet target="ap1"></telnet>
            <ssh target="sta1"></ssh>
            <setvar name=""></setvar>
            <script></script>
            <log-match></log-match>
        </step>
        <step no="6">
            <desc>
            -redo the previous process
            </desc>
            <log-file></log-file>
            <telnet target="ap1"></telnet>
            <ssh target="sta1"></ssh>
            <setvar name=""></setvar>
            <script></script>
            <log-match></log-match>
        </step>

    </stage>
    <failed-process>
        <step no="1..n">
            .. process
	</step>
    </failed-process>
</testcase>
